fnp.py
fnp/__init__.py
fnp/fnp.py
fnp-0.0.5.dist-info/LICENCE.txt
fnp-0.0.5.dist-info/METADATA
fnp-0.0.5.dist-info/WHEEL
fnp-0.0.5.dist-info/top_level.txt
fnp-0.0.5.dist-info/RECORD
